MANIFEST.in
README.rst
requirements.txt
setup.py
jupyterhub_oauth_spawner/__version__.py
jupyterhub_oauth_spawner/oauth_spawner.py
jupyterhub_oauth_spawner.egg-info/PKG-INFO
jupyterhub_oauth_spawner.egg-info/SOURCES.txt
jupyterhub_oauth_spawner.egg-info/dependency_links.txt
jupyterhub_oauth_spawner.egg-info/requires.txt
jupyterhub_oauth_spawner.egg-info/top_level.txt
jupyterhub_oauth_spawner/__pycache__/oauth_spawner.cpython-35.pyc